detaorm/__init__.py
detaorm/base.py
detaorm/client.py
detaorm/field.py
detaorm/paginator.py
detaorm/py.typed
detaorm/query.py
detaorm/types.py
detaorm/undef.py
detaorm/update.py
detaorm-0.4.1.dist-info/LICENSE
detaorm-0.4.1.dist-info/METADATA
detaorm-0.4.1.dist-info/WHEEL
detaorm-0.4.1.dist-info/RECORD
