Metadata-Version: 2.1
Name: detaorm
Version: 0.4.1
Summary: An async ORM for DetaBase.
License: MIT
Author: CircuitSacul
Author-email: circuitsacul@gmail.com
Requires-Python: >=3.8,<4.0
Classifier: License :: OSI Approved :: MIT License
Classifier: Programming Language :: Python :: 3
Classifier: Programming Language :: Python :: 3.8
Classifier: Programming Language :: Python :: 3.9
Classifier: Programming Language :: Python :: 3.10
Classifier: Programming Language :: Python :: 3.11
Requires-Dist: aiohttp (>=3.8.1,<4.0.0)
